yangyijin/__init__.py
yangyijin/yangyijin.py
yangyijin-2.0.1.dist-info/LICENSE
yangyijin-2.0.1.dist-info/METADATA
yangyijin-2.0.1.dist-info/WHEEL
yangyijin-2.0.1.dist-info/top_level.txt
yangyijin-2.0.1.dist-info/RECORD
