Metadata-Version: 2.1
Name: yangyijin
Version: 2.0.1
Summary: This is a test model
Home-page: https://github.com/wistbean/learn_python3_spider
Author: yangyijin
Author-email: 15000733231@163.com
License: UNKNOWN
Platform: UNKNOWN
Classifier: Programming Language :: Python :: 3
Classifier: License :: OSI Approved :: MIT License
Classifier: Operating System :: OS Independent
